{
  "hash": "accf9973",
  "browserHash": "e1cb3c45",
  "optimized": {
    "react": {
      "src": "../../node_modules/react/index.js",
      "file": "react.js",
      "fileHash": "1c4aa52e",
      "needsInterop": true
    },
    "react-dom/client": {
      "src": "../../node_modules/react-dom/client.js",
      "file": "react-dom_client.js",
      "fileHash": "9ebf7774",
      "needsInterop": true
    },
    "react-router-dom": {
      "src": "../../node_modules/react-router-dom/dist/index.js",
      "file": "react-router-dom.js",
      "fileHash": "329de1ce",
      "needsInterop": false
    },
    "react-icons/ai": {
      "src": "../../node_modules/react-icons/ai/index.esm.js",
      "file": "react-icons_ai.js",
      "fileHash": "8dd0860d",
      "needsInterop": false
    },
    "react-icons/fi": {
      "src": "../../node_modules/react-icons/fi/index.esm.js",
      "file": "react-icons_fi.js",
      "fileHash": "5cf80f72",
      "needsInterop": false
    },
    "react-icons/bs": {
      "src": "../../node_modules/react-icons/bs/index.esm.js",
      "file": "react-icons_bs.js",
      "fileHash": "92bc9d2a",
      "needsInterop": false
    },
    "react-icons/fa": {
      "src": "../../node_modules/react-icons/fa/index.esm.js",
      "file": "react-icons_fa.js",
      "fileHash": "8ba8e922",
      "needsInterop": false
    }
  },
  "chunks": {
    "chunk-6TTJTGLE": {
      "file": "chunk-6TTJTGLE.js"
    },
    "chunk-QSQYAWSL": {
      "file": "chunk-QSQYAWSL.js"
    }
  }
}